datasette_public/__init__.py
datasette_public/templates/public_table_change_privacy.html
datasette_public-0.2.3.dist-info/LICENSE
datasette_public-0.2.3.dist-info/METADATA
datasette_public-0.2.3.dist-info/WHEEL
datasette_public-0.2.3.dist-info/entry_points.txt
datasette_public-0.2.3.dist-info/top_level.txt
datasette_public-0.2.3.dist-info/RECORD
