Metadata-Version: 2.1
Name: datasette-public
Version: 0.2.3
Summary: Make specific Datasette tables visible to the public
Home-page: https://github.com/simonw/datasette-public
Author: Simon Willison
License: Apache License, Version 2.0
Project-URL: Issues, https://github.com/simonw/datasette-public/issues
Project-URL: CI, https://github.com/simonw/datasette-public/actions
Project-URL: Changelog, https://github.com/simonw/datasette-public/releases
Classifier: Framework :: Datasette
Classifier: License :: OSI Approved :: Apache Software License
Requires-Python: >=3.7
License-File: LICENSE
Requires-Dist: datasette >=0.63
Provides-Extra: test
Requires-Dist: pytest ; extra == 'test'
Requires-Dist: pytest-asyncio ; extra == 'test'
